CPUの創りかた_渡波/src/cpu_rom.v
module cpu_rom(
   input          clk
  ,input          rstn
  ,input  [4-1:0] addr
  ,output [8-1:0] data
  ,output [8-1:0] data_d
);

  reg [8-1:0] r_reg;

  //ADD A, Im 0000
  //ADD B, Im 0101
  //MOV A, Im 0011
  //MOV B, Im 0111
  //MOV A, B  0001
  //MOV B, A  0100
  //JMP Im    1111
  //JNC Im    1110
  //IN A      0010
  //IN B      0110
  //OUT B     1001
  //OUT Im    1011

  function [8-1:0] romdata;
    input [4-1:0] addr;
    case(addr)
      0:         romdata = 8'b1011_0111;
      1:         romdata = 8'b0000_0001;
      2:         romdata = 8'b1110_0001;
      3:         romdata = 8'b0000_0001;
      4:         romdata = 8'b1110_0011;
      5:         romdata = 8'b1011_0110;
      6:         romdata = 8'b0000_0001;
      7:         romdata = 8'b1110_0110;
      8:         romdata = 8'b0000_0001;
      9:         romdata = 8'b1110_1000;
      10:        romdata = 8'b1011_0000;
      11:        romdata = 8'b1011_0100;
      12:        romdata = 8'b0000_0001;
      13:        romdata = 8'b1110_1010;
      14:        romdata = 8'b1011_1000;
      15:        romdata = 8'b1111_1111;
      default : romdata = 8'bxxxxxxxx;
    endcase
  endfunction

  always @(negedge rstn or posedge clk)  begin
    if (~rstn)
      r_reg <= #1 8'h0;
    else
      r_reg <= #1 data;
  end

  assign data   = romdata(addr);
  assign data_d = r_reg;

endmodule


// module rom_test();
//   reg clk, rstn;

//   reg [4-1:0] addr;
//   reg [8-1:0] data;

//   cpu_rom cpu_rom0(.clk(clk), .rstn(rstn), .addr(addr), .data(data));

//   initial begin
//     addr = 'h0;
//     @(posedge rstn);        
    
//     repeat(16) begin
//       @(posedge clk); #1;addr = addr + 'h1;
//     end
//   end

//   initial begin
//     clk = 0;
//     forever #10 clk = ~clk;
//   end

//   initial begin
//     rstn = 0;
//     #30 rstn = 1;
//   end

//   initial begin
//     #500 $finish();
//   end

//   always @(posedge clk) begin
//     $write("[%t] 0x%h, 0x%h \n", $time, addr, data);
//   end

//   initial begin
//       $dumpfile("rom_test.vcd");
//       $dumpvars(0, rom_test);
//   end

// endmodule

CPUの創りかた_渡波/src/cpu_decoder.v
module cpu_decoder(
   input        clk
  ,input        rstn
  ,input  [3:0] opecode
  ,input        cflag
  ,output [1:0] ds
  ,output [3:0] register 
  ,output [1:0] ds_d
  ,output [3:0] register_d
);

  reg  [1:0] r_ds;
  reg  [3:0] r_register;

  wire [1:0] ds;
  wire [3:0] register;

  wire [5:0] decoder_out;

  function [5:0] decoder; //ds[1] ds[0] load[3][2][1][0]
    input [3:0] code; 
    input       flag; 
    case(code)                    
      4'b0000:        decoder = 6'b000001 ; //ADD A,Im, data select A
      4'b0001:        decoder = 6'b010001 ; //MOV A,B   data select B
      4'b0010:        decoder = 6'b100001 ; //IN  A     data select IN
      4'b0011:        decoder = 6'b110001 ; //MOV A,Im  data select 0 
      4'b0100:        decoder = 6'b000010 ; //MOV B,A   data select A
      4'b0101:        decoder = 6'b010010 ; //ADD B,Im  data select B
      4'b0110:        decoder = 6'b100010 ; //IN  B     data select IN
      4'b0111:        decoder = 6'b110010 ; //MOV B,Im  data select 0
    //4'b1000:        decoder = 6'b ; 
      4'b1001:        decoder = 6'b010100 ; //OUT B     data select B
    //4'b1010:        decoder = 6'b ; 
      4'b1011:        decoder = 6'b110100 ; //OUT Im    data select 0
    //4'b1100:        decoder = 6'b ; 
    //4'b1101:        decoder = 6'b ; 
      4'b1110:        decoder = {2'b11, flag, 3'b000} ; //JNC(C=0)JNC(C=1) data select 0
      4'b1111:        decoder = 6'b111000 ; //JMP
      default:        decoder = 6'bxxxxxx ;
    endcase
  endfunction

  assign decoder_out = decoder(opecode, cflag);

  always @(negedge rstn or posedge clk)  begin
    if (~rstn) begin
      r_ds       <= #1 2'b0;//decoder_out[5:4];
      r_register <= #1 4'b0;//decoder_out[3:0];
    end else begin
      r_ds       <= #1 ds;
      r_register <= #1 register;
    end
  end

  assign ds         = decoder_out[5:4];
  assign register   = decoder_out[3:0];

  assign ds_d       = r_ds;
  assign register_d = r_register;

endmodule


// module decoder_test();
//   reg clk, rstn;

//   reg  [8-1:0] ind;

//   wire [4-1:0] opecode;
//   wire         cflag;
//   reg  [2-1:0] ds;
//   reg  [4-1:0] register;

//   assign opecode = ind[7:4];
//   assign cflag   = ind[3];

//   cpu_decoder cpu_decoder0( .clk(clk) 
//                            ,.rstn(rstn)
//                            ,.opecode(opecode)
//                            ,.cflag(cflag)
//                            ,.ds(ds)
//                            ,.register(register)
//                            );

//   initial begin
//     ind = 'h0;
//     @(posedge rstn);        
    
//     forever begin
//       @(posedge clk); #1;ind = ind + 'h1;
//     end
//   end

//   initial begin
//     clk = 1;
//     forever #5 clk = ~clk;
//   end

//   initial begin
//     rstn = 0;
//     #30 rstn = 1;
//   end

//   initial begin
//     #2600 $finish();
//   end

//   always @(posedge clk) begin
//     $write("[%t] 0x%h : 0x%h, 0x%h, 0x%h, 0x%h \n", $time, ind, opecode, cflag, ds, register);
//   end

//   initial begin
//     $dumpfile("decoder_test.vcd");
//     $dumpvars(0, decoder_test);
//   end

// endmodule

CPUの創りかた_渡波/src/cpu_top.v
module cpu_top(
   input        clk
  ,input        rstn
  ,output [3:0] address
  ,input  [7:0] instruction
  ,input  [3:0] in
  ,output [3:0] out 
);

  wire    [3:0] opecode;
  wire    [3:0] operand;
  wire    [3:0] register;
  wire    [3:0] immidiate;

  wire    [3:0] alu;
  wire    [3:0] y;

  wire    [3:0] load, load_d;

  reg     [3:0] r_a, r_b, r_in, r_pc, r_out;
  
  wire          c; //carryout flag
  reg           r_c; 

  wire    [1:0] ds, ds_d;
  wire          select_b, select_a;
  assign select_b = ds[1];
  assign select_a = ds[0];

  assign opecode   = instruction[7:4];
  assign immidiate = instruction[3:0];

  assign address   = r_pc; 
  assign out       = r_out;

  // select_B, select_Aの順番で書かれているので要注意
  function [3:0] dataselector;
    input         a;
    input         b;
    input [3:0]   c0; //reg A
    input [3:0]   c1; //reg B
    input [3:0]   c2; //reg input
    input [3:0]   c3; //0x0 data 

    // wire sel;
    // assign sel = {select_b, select_a};
    case({b, a})
      2'b11:        dataselector = c3; //0x0, only immidiate 
      2'b01:        dataselector = c2; //reg input
      2'b10:        dataselector = c1; //reg B
      2'b00:        dataselector = c0; //reg A
      default:      dataselector = 'd0;
    endcase
    // always@(*) begin
    //   if      ( select_b &&  select_a)  dataselector = c3;
    //   else if ( select_b && ~select_a)  dataselector = c2;
    //   else if (~select_b &&  select_a)  dataselector = c1;
    //   else if (~select_b && ~select_a)  dataselector = c0;
    //   else                              dataselector = 'd0;
    // end
  endfunction

  assign y = dataselector(select_b, select_a,
                          r_a,
                          r_b,
                          r_in,
                          'd0);

  // ALUは足すだけ
  assign {c, alu} = y + immidiate;


  // LOAD, registers
  always @(negedge rstn or posedge clk) begin
    if     (~rstn)       r_a <= #1 4'd0;
    else if(load[0])     r_a <= #1 alu;
  end
  always @(negedge rstn or posedge clk) begin
    if     (~rstn)       r_b <= #1 4'd0;
    else if(load[1])     r_b <= #1 alu;
  end
  always @(negedge rstn or posedge clk) begin
    if     (~rstn)       r_out <= #1 4'd0;
    else if(load[2])     r_out <= #1 alu;
  end
  always @(negedge rstn or posedge clk) begin
    if     (~rstn)       r_pc <= #1 4'd0;
    else if(load[3])     r_pc <= #1 alu;
    else                 r_pc <= #1 r_pc + 'd1;
  end

  // Carry out
  always @(negedge rstn or posedge clk) begin
    if     (~rstn)       r_c <= #1 1'b0;
    else if(c)           r_c <= #1 1'b1;
    else                 r_c <= #1 1'b0;
  end

  
  always @(negedge rstn or posedge clk) begin
    if  (~rstn)       r_in <= #1 'd0;
    else              r_in <= #1 in;
  end


  // ,input  [4-1:0] opecode
  // ,input          cflag
  // ,output [2-1:0] ds
  // ,output [4-1:0] register 
  cpu_decoder cpu_decoder0( clk
                           ,rstn
                           ,opecode
                           ,~r_c
                           ,ds
                           ,load 
                           ,ds_d
                           ,load_d 
                          );


endmodule 

module test_cpu_top();

  reg clk;
  reg rstn;

  wire [3:0] address;
  wire [7:0] data, data_d;

  wire [3:0] dout;
  reg  [3:0] din;


  initial begin
    clk = 0;
    @(posedge rstn);
    #20;
    clk = 1;
    forever #5 clk = ~clk;
  end

  initial begin
    rstn = 0;
    din  = 0;
    #30 rstn = 1;

    @(posedge clk);
    din = 4'b1010;
  end



  initial begin
    #2600 $finish();
  end


  cpu_top cpu_top0( clk         // input          clk
                   ,rstn        // ,input          rstn
                   ,address     // ,output [4-1:0] address
                   ,data // ,input  [8-1:0] instruction
                   ,din          // ,output [4-1:0] in
                   ,dout         // ,output [4-1:0] out
                  );


  cpu_rom cpu_rom0( clk
                   ,rstn
                   ,address
                   ,data
                   ,data_d
                  );

  initial begin
    $dumpfile("cpu_top_test.vcd");
    $dumpvars(0, test_cpu_top);
  end


endmodule

CPUの創りかた_渡波/work/cpu_top_test.vcd
$date
	Sat Feb 22 18:39:21 2020
$end
$version
	Icarus Verilog
$end
$timescale
	1s
$end
$scope module test_cpu_top $end
$var wire 4 ! dout [3:0] $end
$var wire 8 " data_d [7:0] $end
$var wire 8 # data [7:0] $end
$var wire 4 $ address [3:0] $end
$var reg 1 % clk $end
$var reg 4 & din [3:0] $end
$var reg 1 ' rstn $end
$scope module cpu_rom0 $end
$var wire 1 % clk $end
$var wire 8 ( data_d [7:0] $end
$var wire 1 ' rstn $end
$var wire 8 ) data [7:0] $end
$var wire 4 * addr [3:0] $end
$var reg 8 + r_reg [7:0] $end
$scope function romdata $end
$var reg 4 , addr [3:0] $end
$var reg 8 - romdata [7:0] $end
$upscope $end
$upscope $end
$scope module cpu_top0 $end
$var wire 1 % clk $end
$var wire 4 . in [3:0] $end
$var wire 8 / instruction [7:0] $end
$var wire 4 0 out [3:0] $end
$var wire 1 ' rstn $end
$var wire 4 1 y [3:0] $end
$var wire 1 2 select_b $end
$var wire 1 3 select_a $end
$var wire 4 4 opecode [3:0] $end
$var wire 4 5 load_d [3:0] $end
$var wire 4 6 load [3:0] $end
$var wire 4 7 immidiate [3:0] $end
$var wire 2 8 ds_d [1:0] $end
$var wire 2 9 ds [1:0] $end
$var wire 1 : c $end
$var wire 4 ; alu [3:0] $end
$var wire 4 < address [3:0] $end
$var reg 4 = r_a [3:0] $end
$var reg 4 > r_b [3:0] $end
$var reg 1 ? r_c $end
$var reg 4 @ r_in [3:0] $end
$var reg 4 A r_out [3:0] $end
$var reg 4 B r_pc [3:0] $end
$scope function dataselector $end
$var reg 1 C a $end
$var reg 1 D b $end
$var reg 4 E c0 [3:0] $end
$var reg 4 F c1 [3:0] $end
$var reg 4 G c2 [3:0] $end
$var reg 4 H c3 [3:0] $end
$var reg 4 I dataselector [3:0] $end
$upscope $end
$scope module cpu_decoder0 $end
$var wire 1 J cflag $end
$var wire 1 % clk $end
$var wire 2 K ds_d [1:0] $end
$var wire 4 L opecode [3:0] $end
$var wire 4 M register_d [3:0] $end
$var wire 1 ' rstn $end
$var wire 4 N register [3:0] $end
$var wire 2 O ds [1:0] $end
$var wire 6 P decoder_out [5:0] $end
$var reg 2 Q r_ds [1:0] $end
$var reg 4 R r_register [3:0] $end
$scope function decoder $end
$var reg 4 S code [3:0] $end
$var reg 6 T decoder [5:0] $end
$var reg 1 U flag $end
$upscope $end
$upscope $end
$upscope $end
$upscope $end
$enddefinitions $end
#0
$dumpvars
xU
bx T
bx S
bx R
bx Q
bx P
bx O
bx N
bx M
bx L
bx K
xJ
b0 I
b0 H
bx G
bx F
bx E
xD
xC
bx B
bx A
bx @
x?
bx >
bx =
bx <
bx ;
x:
bx 9
bx 8
bx 7
bx 6
bx 5
bx 4
x3
x2
b0 1
bx 0
bx /
b0 .
bx -
bx ,
bx +
bx *
bx )
bx (
0'
b0 &
0%
bx $
bx #
bx "
bx !
$end
#1
1D
1C
13
12
b11 9
b11 O
b100 6
b100 N
b110100 P
b110100 T
b1011 S
b111 ;
0:
b1011 4
b1011 L
b111 7
1U
b10110111 #
b10110111 )
b10110111 /
b10110111 -
b0 ,
1J
b0 G
b0 F
b0 E
b0 5
b0 M
b0 R
b0 8
b0 K
b0 Q
b0 =
b0 >
b0 !
b0 0
b0 A
b0 $
b0 *
b0 <
b0 B
0?
b0 @
b0 "
b0 (
b0 +
#30
1'
#50
b1010 &
b1010 .
1%
#51
0D
0C
03
02
b0 9
b0 O
b1 6
b1 N
b1 P
b1 T
b0 S
b1 ;
b0 4
b0 L
b1 7
b1010 G
b1 #
b1 )
b1 /
b1 -
b1 ,
b10110111 "
b10110111 (
b10110111 +
b1010 @
b1 $
b1 *
b1 <
b1 B
b111 !
b111 0
b111 A
b100 5
b100 M
b100 R
b11 8
b11 K
b11 Q
#55
0%
#60
1%
#61
1D
1C
13
12
b11 9
b11 O
b1000 6
b1000 N
b111000 P
b111000 T
b1110 S
b1 ;
b1110 4
b1110 L
b0 1
b0 I
b1 E
b11100001 #
b11100001 )
b11100001 /
b11100001 -
b10 ,
b1 5
b1 M
b1 R
b0 8
b0 K
b0 Q
b1 =
b10 $
b10 *
b10 <
b10 B
b1 "
b1 (
b1 +
#65
0%
#70
1%
#71
b10 ;
b1 1
b1 I
0D
0C
03
02
b0 9
b0 O
b1 6
b1 N
b1 P
b1 T
b0 S
b0 4
b0 L
b1 #
b1 )
b1 /
b1 -
b1 ,
b11100001 "
b11100001 (
b11100001 +
b1 $
b1 *
b1 <
b1 B
b1000 5
b1000 M
b1000 R
b11 8
b11 K
b11 Q
#75
0%
#80
1%
#81
1D
1C
13
12
b11 9
b11 O
b1000 6
b1000 N
b111000 P
b111000 T
b1110 S
b1 ;
b1110 4
b1110 L
b0 1
b0 I
b10 E
b11100001 #
b11100001 )
b11100001 /
b11100001 -
b10 ,
b1 5
b1 M
b1 R
b0 8
b0 K
b0 Q
b10 =
b10 $
b10 *
b10 <
b10 B
b1 "
b1 (
b1 +
#85
0%
#90
1%
#91
b11 ;
b10 1
b10 I
0D
0C
03
02
b0 9
b0 O
b1 6
b1 N
b1 P
b1 T
b0 S
b0 4
b0 L
b1 #
b1 )
b1 /
b1 -
b1 ,
b11100001 "
b11100001 (
b11100001 +
b1 $
b1 *
b1 <
b1 B
b1000 5
b1000 M
b1000 R
b11 8
b11 K
b11 Q
#95
0%
#100
1%
#101
1D
1C
13
12
b11 9
b11 O
b1000 6
b1000 N
b111000 P
b111000 T
b1110 S
b1 ;
b1110 4
b1110 L
b0 1
b0 I
b11 E
b11100001 #
b11100001 )
b11100001 /
b11100001 -
b10 ,
b1 5
b1 M
b1 R
b0 8
b0 K
b0 Q
b11 =
b10 $
b10 *
b10 <
b10 B
b1 "
b1 (
b1 +
#105
0%
#110
1%
#111
b100 ;
b11 1
b11 I
0D
0C
03
02
b0 9
b0 O
b1 6
b1 N
b1 P
b1 T
b0 S
b0 4
b0 L
b1 #
b1 )
b1 /
b1 -
b1 ,
b11100001 "
b11100001 (
b11100001 +
b1 $
b1 *
b1 <
b1 B
b1000 5
b1000 M
b1000 R
b11 8
b11 K
b11 Q
#115
0%
#120
1%
#121
1D
1C
13
12
b11 9
b11 O
b1000 6
b1000 N
b111000 P
b111000 T
b1110 S
b1 ;
b1110 4
b1110 L
b0 1
b0 I
b100 E
b11100001 #
b11100001 )
b11100001 /
b11100001 -
b10 ,
b1 5
b1 M
b1 R
b0 8
b0 K
b0 Q
b100 =
b10 $
b10 *
b10 <
b10 B
b1 "
b1 (
b1 +
#125
0%
#130
1%
#131
b101 ;
b100 1
b100 I
0D
0C
03
02
b0 9
b0 O
b1 6
b1 N
b1 P
b1 T
b0 S
b0 4
b0 L
b1 #
b1 )
b1 /
b1 -
b1 ,
b11100001 "
b11100001 (
b11100001 +
b1 $
b1 *
b1 <
b1 B
b1000 5
b1000 M
b1000 R
b11 8
b11 K
b11 Q
#135
0%
#140
1%
#141
1D
1C
13
12
b11 9
b11 O
b1000 6
b1000 N
b111000 P
b111000 T
b1110 S
b1 ;
b1110 4
b1110 L
b0 1
b0 I
b101 E
b11100001 #
b11100001 )
b11100001 /
b11100001 -
b10 ,
b1 5
b1 M
b1 R
b0 8
b0 K
b0 Q
b101 =
b10 $
b10 *
b10 <
b10 B
b1 "
b1 (
b1 +
#145
0%
#150
1%
#151
b110 ;
b101 1
b101 I
0D
0C
03
02
b0 9
b0 O
b1 6
b1 N
b1 P
b1 T
b0 S
b0 4
b0 L
b1 #
b1 )
b1 /
b1 -
b1 ,
b11100001 "
b11100001 (
b11100001 +
b1 $
b1 *
b1 <
b1 B
b1000 5
b1000 M
b1000 R
b11 8
b11 K
b11 Q
#155
0%
#160
1%
#161
1D
1C
13
12
b11 9
b11 O
b1000 6
b1000 N
b111000 P
b111000 T
b1110 S
b1 ;
b1110 4
b1110 L
b0 1
b0 I
b110 E
b11100001 #
b11100001 )
b11100001 /
b11100001 -
b10 ,
b1 5
b1 M
b1 R
b0 8
b0 K
b0 Q
b110 =
b10 $
b10 *
b10 <
b10 B
b1 "
b1 (
b1 +
#165
0%
#170
1%
#171
b111 ;
b110 1
b110 I
0D
0C
03
02
b0 9
b0 O
b1 6
b1 N
b1 P
b1 T
b0 S
b0 4
b0 L
b1 #
b1 )
b1 /
b1 -
b1 ,
b11100001 "
b11100001 (
b11100001 +
b1 $
b1 *
b1 <
b1 B
b1000 5
b1000 M
b1000 R
b11 8
b11 K
b11 Q
#175
0%
#180
1%
#181
1D
1C
13
12
b11 9
b11 O
b1000 6
b1000 N
b111000 P
b111000 T
b1110 S
b1 ;
b1110 4
b1110 L
b0 1
b0 I
b111 E
b11100001 #
b11100001 )
b11100001 /
b11100001 -
b10 ,
b1 5
b1 M
b1 R
b0 8
b0 K
b0 Q
b111 =
b10 $
b10 *
b10 <
b10 B
b1 "
b1 (
b1 +
#185
0%
#190
1%
#191
b1000 ;
b111 1
b111 I
0D
0C
03
02
b0 9
b0 O
b1 6
b1 N
b1 P
b1 T
b0 S
b0 4
b0 L
b1 #
b1 )
b1 /
b1 -
b1 ,
b11100001 "
b11100001 (
b11100001 +
b1 $
b1 *
b1 <
b1 B
b1000 5
b1000 M
b1000 R
b11 8
b11 K
b11 Q
#195
0%
#200
1%
#201
1D
1C
13
12
b11 9
b11 O
b1000 6
b1000 N
b111000 P
b111000 T
b1110 S
b1 ;
b1110 4
b1110 L
b0 1
b0 I
b1000 E
b11100001 #
b11100001 )
b11100001 /
b11100001 -
b10 ,
b1 5
b1 M
b1 R
b0 8
b0 K
b0 Q
b1000 =
b10 $
b10 *
b10 <
b10 B
b1 "
b1 (
b1 +
#205
0%
#210
1%
#211
b1001 ;
b1000 1
b1000 I
0D
0C
03
02
b0 9
b0 O
b1 6
b1 N
b1 P
b1 T
b0 S
b0 4
b0 L
b1 #
b1 )
b1 /
b1 -
b1 ,
b11100001 "
b11100001 (
b11100001 +
b1 $
b1 *
b1 <
b1 B
b1000 5
b1000 M
b1000 R
b11 8
b11 K
b11 Q
#215
0%
#220
1%
#221
1D
1C
13
12
b11 9
b11 O
b1000 6
b1000 N
b111000 P
b111000 T
b1110 S
b1 ;
b1110 4
b1110 L
b0 1
b0 I
b1001 E
b11100001 #
b11100001 )
b11100001 /
b11100001 -
b10 ,
b1 5
b1 M
b1 R
b0 8
b0 K
b0 Q
b1001 =
b10 $
b10 *
b10 <
b10 B
b1 "
b1 (
b1 +
#225
0%
#230
1%
#231
b1010 ;
b1001 1
b1001 I
0D
0C
03
02
b0 9
b0 O
b1 6
b1 N
b1 P
b1 T
b0 S
b0 4
b0 L
b1 #
b1 )
b1 /
b1 -
b1 ,
b11100001 "
b11100001 (
b11100001 +
b1 $
b1 *
b1 <
b1 B
b1000 5
b1000 M
b1000 R
b11 8
b11 K
b11 Q
#235
0%
#240
1%
#241
1D
1C
13
12
b11 9
b11 O
b1000 6
b1000 N
b111000 P
b111000 T
b1110 S
b1 ;
b1110 4
b1110 L
b0 1
b0 I
b1010 E
b11100001 #
b11100001 )
b11100001 /
b11100001 -
b10 ,
b1 5
b1 M
b1 R
b0 8
b0 K
b0 Q
b1010 =
b10 $
b10 *
b10 <
b10 B
b1 "
b1 (
b1 +
#245
0%
#250
1%
#251
b1011 ;
b1010 1
b1010 I
0D
0C
03
02
b0 9
b0 O
b1 6
b1 N
b1 P
b1 T
b0 S
b0 4
b0 L
b1 #
b1 )
b1 /
b1 -
b1 ,
b11100001 "
b11100001 (
b11100001 +
b1 $
b1 *
b1 <
b1 B
b1000 5
b1000 M
b1000 R
b11 8
b11 K
b11 Q
#255
0%
#260
1%
#261
1D
1C
13
12
b11 9
b11 O
b1000 6
b1000 N
b111000 P
b111000 T
b1110 S
b1 ;
b1110 4
b1110 L
b0 1
b0 I
b1011 E
b11100001 #
b11100001 )
b11100001 /
b11100001 -
b10 ,
b1 5
b1 M
b1 R
b0 8
b0 K
b0 Q
b1011 =
b10 $
b10 *
b10 <
b10 B
b1 "
b1 (
b1 +
#265
0%
#270
1%
#271
b1100 ;
b1011 1
b1011 I
0D
0C
03
02
b0 9
b0 O
b1 6
b1 N
b1 P
b1 T
b0 S
b0 4
b0 L
b1 #
b1 )
b1 /
b1 -
b1 ,
b11100001 "
b11100001 (
b11100001 +
b1 $
b1 *
b1 <
b1 B
b1000 5
b1000 M
b1000 R
b11 8
b11 K
b11 Q
#275
0%
#280
1%
#281
1D
1C
13
12
b11 9
b11 O
b1000 6
b1000 N
b111000 P
b111000 T
b1110 S
b1 ;
b1110 4
b1110 L
b0 1
b0 I
b1100 E
b11100001 #
b11100001 )
b11100001 /
b11100001 -
b10 ,
b1 5
b1 M
b1 R
b0 8
b0 K
b0 Q
b1100 =
b10 $
b10 *
b10 <
b10 B
b1 "
b1 (
b1 +
#285
0%
#290
1%
#291
b1101 ;
b1100 1
b1100 I
0D
0C
03
02
b0 9
b0 O
b1 6
b1 N
b1 P
b1 T
b0 S
b0 4
b0 L
b1 #
b1 )
b1 /
b1 -
b1 ,
b11100001 "
b11100001 (
b11100001 +
b1 $
b1 *
b1 <
b1 B
b1000 5
b1000 M
b1000 R
b11 8
b11 K
b11 Q
#295
0%
#300
1%
#301
1D
1C
13
12
b11 9
b11 O
b1000 6
b1000 N
b111000 P
b111000 T
b1110 S
b1 ;
b1110 4
b1110 L
b0 1
b0 I
b1101 E
b11100001 #
b11100001 )
b11100001 /
b11100001 -
b10 ,
b1 5
b1 M
b1 R
b0 8
b0 K
b0 Q
b1101 =
b10 $
b10 *
b10 <
b10 B
b1 "
b1 (
b1 +
#305
0%
#310
1%
#311
b1110 ;
b1101 1
b1101 I
0D
0C
03
02
b0 9
b0 O
b1 6
b1 N
b1 P
b1 T
b0 S
b0 4
b0 L
b1 #
b1 )
b1 /
b1 -
b1 ,
b11100001 "
b11100001 (
b11100001 +
b1 $
b1 *
b1 <
b1 B
b1000 5
b1000 M
b1000 R
b11 8
b11 K
b11 Q
#315
0%
#320
1%
#321
1D
1C
13
12
b11 9
b11 O
b1000 6
b1000 N
b111000 P
b111000 T
b1110 S
b1 ;
b1110 4
b1110 L
b0 1
b0 I
b1110 E
b11100001 #
b11100001 )
b11100001 /
b11100001 -
b10 ,
b1 5
b1 M
b1 R
b0 8
b0 K
b0 Q
b1110 =
b10 $
b10 *
b10 <
b10 B
b1 "
b1 (
b1 +
#325
0%
#330
1%
#331
b1111 ;
b1110 1
b1110 I
0D
0C
03
02
b0 9
b0 O
b1 6
b1 N
b1 P
b1 T
b0 S
b0 4
b0 L
b1 #
b1 )
b1 /
b1 -
b1 ,
b11100001 "
b11100001 (
b11100001 +
b1 $
b1 *
b1 <
b1 B
b1000 5
b1000 M
b1000 R
b11 8
b11 K
b11 Q
#335
0%
#340
1%
#341
1D
1C
13
12
b11 9
b11 O
b1000 6
b1000 N
b111000 P
b111000 T
b1110 S
b1 ;
0:
b1110 4
b1110 L
b0 1
b0 I
b1111 E
b11100001 #
b11100001 )
b11100001 /
b11100001 -
b10 ,
b1 5
b1 M
b1 R
b0 8
b0 K
b0 Q
b1111 =
b10 $
b10 *
b10 <
b10 B
b1 "
b1 (
b1 +
#345
0%
#350
1%
#351
b0 ;
1:
b1111 1
b1111 I
0D
0C
03
02
b0 9
b0 O
b1 6
b1 N
b1 P
b1 T
b0 S
b0 4
b0 L
b1 #
b1 )
b1 /
b1 -
b1 ,
b11100001 "
b11100001 (
b11100001 +
b1 $
b1 *
b1 <
b1 B
b1000 5
b1000 M
b1000 R
b11 8
b11 K
b11 Q
#355
0%
#360
1%
#361
1D
1C
13
12
b11 9
b11 O
b0 6
b0 N
b110000 P
b110000 T
b1110 S
b1 ;
0:
b1110 4
b1110 L
0U
b0 1
b0 I
b0 E
b11100001 #
b11100001 )
b11100001 /
b11100001 -
b10 ,
0J
b1 5
b1 M
b1 R
b0 8
b0 K
b0 Q
b0 =
b10 $
b10 *
b10 <
b10 B
1?
b1 "
b1 (
b1 +
#365
0%
#370
1%
#371
0D
0C
03
02
b0 9
b0 O
b1 6
b1 N
b1 P
b1 T
1U
b0 S
b0 4
b0 L
1J
b1 #
b1 )
b1 /
b1 -
b11 ,
b11100001 "
b11100001 (
b11100001 +
0?
b11 $
b11 *
b11 <
b11 B
b0 5
b0 M
b0 R
b11 8
b11 K
b11 Q
#375
0%
#380
1%
#381
1D
1C
13
12
b11 9
b11 O
b1000 6
b1000 N
b111000 P
b111000 T
b1110 S
b11 ;
b1110 4
b1110 L
b11 7
b0 1
b0 I
b1 E
b11100011 #
b11100011 )
b11100011 /
b11100011 -
b100 ,
b1 5
b1 M
b1 R
b0 8
b0 K
b0 Q
b1 =
b100 $
b100 *
b100 <
b100 B
b1 "
b1 (
b1 +
#385
0%
#390
1%
#391
b1 1
b1 I
0D
0C
03
02
b0 9
b0 O
b1 6
b1 N
b1 P
b1 T
b0 S
b10 ;
b0 4
b0 L
b1 7
b1 #
b1 )
b1 /
b1 -
b11 ,
b11100011 "
b11100011 (
b11100011 +
b11 $
b11 *
b11 <
b11 B
b1000 5
b1000 M
b1000 R
b11 8
b11 K
b11 Q
#395
0%
#400
1%
#401
1D
1C
13
12
b11 9
b11 O
b1000 6
b1000 N
b111000 P
b111000 T
b1110 S
b11 ;
b1110 4
b1110 L
b11 7
b0 1
b0 I
b10 E
b11100011 #
b11100011 )
b11100011 /
b11100011 -
b100 ,
b1 5
b1 M
b1 R
b0 8
b0 K
b0 Q
b10 =
b100 $
b100 *
b100 <
b100 B
b1 "
b1 (
b1 +
#405
0%
#410
1%
#411
b10 1
b10 I
0D
0C
03
02
b0 9
b0 O
b1 6
b1 N
b1 P
b1 T
b0 S
b11 ;
b0 4
b0 L
b1 7
b1 #
b1 )
b1 /
b1 -
b11 ,
b11100011 "
b11100011 (
b11100011 +
b11 $
b11 *
b11 <
b11 B
b1000 5
b1000 M
b1000 R
b11 8
b11 K
b11 Q
#415
0%
#420
1%
#421
1D
1C
13
12
b11 9
b11 O
b1000 6
b1000 N
b111000 P
b111000 T
b1110 S
b11 ;
b1110 4
b1110 L
b11 7
b0 1
b0 I
b11 E
b11100011 #
b11100011 )
b11100011 /
b11100011 -
b100 ,
b1 5
b1 M
b1 R
b0 8
b0 K
b0 Q
b11 =
b100 $
b100 *
b100 <
b100 B
b1 "
b1 (
b1 +
#425
0%
#430
1%
#431
b11 1
b11 I
0D
0C
03
02
b0 9
b0 O
b1 6
b1 N
b1 P
b1 T
b0 S
b100 ;
b0 4
b0 L
b1 7
b1 #
b1 )
b1 /
b1 -
b11 ,
b11100011 "
b11100011 (
b11100011 +
b11 $
b11 *
b11 <
b11 B
b1000 5
b1000 M
b1000 R
b11 8
b11 K
b11 Q
#435
0%
#440
1%
#441
1D
1C
13
12
b11 9
b11 O
b1000 6
b1000 N
b111000 P
b111000 T
b1110 S
b11 ;
b1110 4
b1110 L
b11 7
b0 1
b0 I
b100 E
b11100011 #
b11100011 )
b11100011 /
b11100011 -
b100 ,
b1 5
b1 M
b1 R
b0 8
b0 K
b0 Q
b100 =
b100 $
b100 *
b100 <
b100 B
b1 "
b1 (
b1 +
#445
0%
#450
1%
#451
b100 1
b100 I
0D
0C
03
02
b0 9
b0 O
b1 6
b1 N
b1 P
b1 T
b0 S
b101 ;
b0 4
b0 L
b1 7
b1 #
b1 )
b1 /
b1 -
b11 ,
b11100011 "
b11100011 (
b11100011 +
b11 $
b11 *
b11 <
b11 B
b1000 5
b1000 M
b1000 R
b11 8
b11 K
b11 Q
#455
0%
#460
1%
#461
1D
1C
13
12
b11 9
b11 O
b1000 6
b1000 N
b111000 P
b111000 T
b1110 S
b11 ;
b1110 4
b1110 L
b11 7
b0 1
b0 I
b101 E
b11100011 #
b11100011 )
b11100011 /
b11100011 -
b100 ,
b1 5
b1 M
b1 R
b0 8
b0 K
b0 Q
b101 =
b100 $
b100 *
b100 <
b100 B
b1 "
b1 (
b1 +
#465
0%
#470
1%
#471
b101 1
b101 I
0D
0C
03
02
b0 9
b0 O
b1 6
b1 N
b1 P
b1 T
b0 S
b110 ;
b0 4
b0 L
b1 7
b1 #
b1 )
b1 /
b1 -
b11 ,
b11100011 "
b11100011 (
b11100011 +
b11 $
b11 *
b11 <
b11 B
b1000 5
b1000 M
b1000 R
b11 8
b11 K
b11 Q
#475
0%
#480
1%
#481
1D
1C
13
12
b11 9
b11 O
b1000 6
b1000 N
b111000 P
b111000 T
b1110 S
b11 ;
b1110 4
b1110 L
b11 7
b0 1
b0 I
b110 E
b11100011 #
b11100011 )
b11100011 /
b11100011 -
b100 ,
b1 5
b1 M
b1 R
b0 8
b0 K
b0 Q
b110 =
b100 $
b100 *
b100 <
b100 B
b1 "
b1 (
b1 +
#485
0%
#490
1%
